src/rtl/traffic_light.sv
module traffic_light 
#(
    parameter int GREEN_CYCLE_LENGTH = 10,
    parameter int YELLOW_CYCLE_LENGTH = 3
)
(
    input clk,
    input rst_n,

    output ns_g_o,
    output ns_y_o,
    output ns_r_o,
    output ew_g_o,
    output ew_y_o,
    output ew_r_o
);
typedef enum {NS_GREEN, NS_YELLOW, EW_GREEN, EW_YELLOW} state_t;
state_t curr_state, next_state;

logic [31:0] cnt_next, cnt;

logic ns_g;
logic ns_y;
logic ns_r;
logic ew_g;
logic ew_y;
logic ew_r;

always_ff @(posedge clk) begin
    if(~rst_n) begin
        curr_state <= NS_GREEN;
        cnt <= '0;
    end else begin 
        curr_state <= next_state;
        cnt <= cnt_next;
    end
end

always_comb begin
  case (curr_state)
    NS_GREEN: begin
        if (cnt == GREEN_CYCLE_LENGTH-1) begin
            cnt_next = 0;
            next_state = NS_YELLOW;
        end else begin
            cnt_next = cnt + 1;
            next_state = NS_GREEN;
        end
        ns_g = 1'b1;
        ns_y = 1'b0;
        ns_r = 1'b0;
        ew_g = 1'b0;
        ew_y = 1'b0;
        ew_r = 1'b1;
    end
        
    NS_YELLOW: begin
        if (cnt == YELLOW_CYCLE_LENGTH-1) begin
            cnt_next = 0;
            next_state = EW_GREEN;
        end else begin
            cnt_next = cnt + 1;
            next_state = NS_YELLOW;
        end
        ns_g = 1'b0;
        ns_y = 1'b1;
        ns_r = 1'b0;
        ew_g = 1'b0;
        ew_y = 1'b0;
        ew_r = 1'b1;
    end
    EW_GREEN: begin
        if (cnt == GREEN_CYCLE_LENGTH-1) begin
            cnt_next = 0;
            next_state = EW_YELLOW;
        end else begin
            cnt_next = cnt + 1;
            next_state = EW_GREEN;
        end
        ns_g = 1'b0;
        ns_y = 1'b0;
        ns_r = 1'b1;
        ew_g = 1'b1;
        ew_y = 1'b0;
        ew_r = 1'b0;
    end
    EW_YELLOW: begin
        if (cnt == YELLOW_CYCLE_LENGTH-1) begin
            cnt_next = 0;
            next_state = NS_GREEN;
        end else begin
            cnt_next = cnt + 1;
            next_state = EW_YELLOW;
        end
        ns_g = 1'b0;
        ns_y = 1'b0;
        ns_r = 1'b1;
        ew_g = 1'b0;
        ew_y = 1'b1;
        ew_r = 1'b0;
    end
    endcase 
end

assign ns_g_o = ns_g;
assign ns_y_o = ns_y;
assign ns_r_o = ns_r;
assign ew_g_o = ew_g;
assign ew_y_o = ew_y;
assign ew_r_o = ew_r;

endmodule

src/tb/tb_traffic_light.sv
module tb_traffic_light;
    logic clk;
    logic rst_n;
    logic ns_g, ns_y, ns_r;
    logic ew_g, ew_y, ew_r;
    
    traffic_light
    dut
    (
        .clk (clk),
        .rst_n (rst_n),
        .ns_g_o(ns_g),
        .ns_y_o(ns_y),
        .ns_r_o(ns_r),
        .ew_g_o(ew_g),
        .ew_y_o(ew_y),
        .ew_r_o(ew_r)
    );

    initial begin 
        clk = 0;
        forever begin
            #10 clk = ~clk;
        end 
    end

    initial begin
        #100
        rst_n = 1'b0;
        #100
        rst_n = 1'b1;
    end 

    initial begin
        $dumpfile("wave.vcd");
        $dumpvars(0, tb_traffic_light);
        $display("Hello, start of test %0t", $time);
      #100000;
        #20
        $finish;
    end
endmodule

src/wave.vcd
$version Generated by VerilatedVcd $end
$timescale 1ps $end
 $scope module $rootio $end
 $upscope $end
 $scope module tb_traffic_light $end
  $var wire 1 - clk $end
  $var wire 1 . rst_n $end
  $var wire 1 # ns_g $end
  $var wire 1 $ ns_y $end
  $var wire 1 % ns_r $end
  $var wire 1 & ew_g $end
  $var wire 1 ' ew_y $end
  $var wire 1 ( ew_r $end
  $scope module dut $end
   $var wire 32 / GREEN_CYCLE_LENGTH [31:0] $end
   $var wire 32 0 YELLOW_CYCLE_LENGTH [31:0] $end
   $var wire 1 - clk $end
   $var wire 1 . rst_n $end
   $var wire 1 # ns_g_o $end
   $var wire 1 $ ns_y_o $end
   $var wire 1 % ns_r_o $end
   $var wire 1 & ew_g_o $end
   $var wire 1 ' ew_y_o $end
   $var wire 1 ( ew_r_o $end
   $var wire 32 ) curr_state [31:0] $end
   $var wire 32 * next_state [31:0] $end
   $var wire 32 + cnt_next [31:0] $end
   $var wire 32 , cnt [31:0] $end
   $var wire 1 # ns_g $end
   $var wire 1 $ ns_y $end
   $var wire 1 % ns_r $end
   $var wire 1 & ew_g $end
   $var wire 1 ' ew_y $end
   $var wire 1 ( ew_r $end
  $upscope $end
 $upscope $end
$enddefinitions $end


#0
1#
0$
0%
0&
0'
1(
b00000000000000000000000000000000 )
b00000000000000000000000000000000 *
b00000000000000000000000000000001 +
b00000000000000000000000000000000 ,
0-
0.
b00000000000000000000000000001010 /
b00000000000000000000000000000011 0
#10
1-
#20
0-
#30
1-
#40
0-
#50
1-
#60
0-
#70
1-
#80
0-
#90
1-
#100
0-
#110
1-
#120
0-
#130
1-
#140
0-
#150
1-
#160
0-
#170
1-
#180
0-
#190
1-
#200
0-
1.
#210
b00000000000000000000000000000010 +
b00000000000000000000000000000001 ,
1-
#220
0-
#230
b00000000000000000000000000000011 +
b00000000000000000000000000000010 ,
1-
#240
0-
#250
b00000000000000000000000000000100 +
b00000000000000000000000000000011 ,
1-
#260
0-
#270
b00000000000000000000000000000101 +
b00000000000000000000000000000100 ,
1-
#280
0-
#290
b00000000000000000000000000000110 +
b00000000000000000000000000000101 ,
1-
#300
0-
#310
b00000000000000000000000000000111 +
b00000000000000000000000000000110 ,
1-
#320
0-
#330
b00000000000000000000000000001000 +
b00000000000000000000000000000111 ,
1-
#340
0-
#350
b00000000000000000000000000001001 +
b00000000000000000000000000001000 ,
1-
#360
0-
#370
b00000000000000000000000000000001 *
b00000000000000000000000000000000 +
b00000000000000000000000000001001 ,
1-
#380
0-
#390
0#
1$
b00000000000000000000000000000001 )
b00000000000000000000000000000001 +
b00000000000000000000000000000000 ,
1-
#400
0-
#410
b00000000000000000000000000000010 +
b00000000000000000000000000000001 ,
1-
#420
0-
#430
b00000000000000000000000000000010 *
b00000000000000000000000000000000 +
b00000000000000000000000000000010 ,
1-
#440
0-
#450
0$
1%
1&
0(
b00000000000000000000000000000010 )
b00000000000000000000000000000001 +
b00000000000000000000000000000000 ,
1-
#460
0-
#470
b00000000000000000000000000000010 +
b00000000000000000000000000000001 ,
1-
#480
0-
#490
b00000000000000000000000000000011 +
b00000000000000000000000000000010 ,
1-
#500
0-
#510
b00000000000000000000000000000100 +
b00000000000000000000000000000011 ,
1-
#520
0-
#530
b00000000000000000000000000000101 +
b00000000000000000000000000000100 ,
1-
#540
0-
#550
b00000000000000000000000000000110 +
b00000000000000000000000000000101 ,
1-
#560
0-
#570
b00000000000000000000000000000111 +
b00000000000000000000000000000110 ,
1-
#580
0-
#590
b00000000000000000000000000001000 +
b00000000000000000000000000000111 ,
1-
#600
0-
#610
b00000000000000000000000000001001 +
b00000000000000000000000000001000 ,
1-
#620
0-
#630
b00000000000000000000000000000011 *
b00000000000000000000000000000000 +
b00000000000000000000000000001001 ,
1-
#640
0-
#650
0&
1'
b00000000000000000000000000000011 )
b00000000000000000000000000000001 +
b00000000000000000000000000000000 ,
1-
#660
0-
#670
b00000000000000000000000000000010 +
b00000000000000000000000000000001 ,
1-
#680
0-
#690
b00000000000000000000000000000000 *
b00000000000000000000000000000000 +
b00000000000000000000000000000010 ,
1-
#700
0-
#710
1#
0%
0'
1(
b00000000000000000000000000000000 )
b00000000000000000000000000000001 +
b00000000000000000000000000000000 ,
1-
#720
0-
#730
b00000000000000000000000000000010 +
b00000000000000000000000000000001 ,
1-
#740
0-
#750
b00000000000000000000000000000011 +
b00000000000000000000000000000010 ,
1-
#760
0-
#770
b00000000000000000000000000000100 +
b00000000000000000000000000000011 ,
1-
#780
0-
#790
b00000000000000000000000000000101 +
b00000000000000000000000000000100 ,
1-
#800
0-
#810
b00000000000000000000000000000110 +
b00000000000000000000000000000101 ,
1-
#820
0-
#830
b00000000000000000000000000000111 +
b00000000000000000000000000000110 ,
1-
#840
0-
#850
b00000000000000000000000000001000 +
b00000000000000000000000000000111 ,
1-
#860
0-
#870
b00000000000000000000000000001001 +
b00000000000000000000000000001000 ,
1-
#880
0-
#890
b00000000000000000000000000000001 *
b00000000000000000000000000000000 +
b00000000000000000000000000001001 ,
1-
#900
0-
#910
0#
1$
b00000000000000000000000000000001 )
b00000000000000000000000000000001 +
b00000000000000000000000000000000 ,
1-
#920
0-
#930
b00000000000000000000000000000010 +
b00000000000000000000000000000001 ,
1-
#940
0-
#950
b00000000000000000000000000000010 *
b00000000000000000000000000000000 +
b00000000000000000000000000000010 ,
1-
#960
0-
#970
0$
1%
1&
0(
b00000000000000000000000000000010 )
b00000000000000000000000000000001 +
b00000000000000000000000000000000 ,
1-
#980
0-
#990
b00000000000000000000000000000010 +
b00000000000000000000000000000001 ,
1-
#1000
0-
#1010
b00000000000000000000000000000011 +
b00000000000000000000000000000010 ,
1-
#1020
0-
#1030
b00000000000000000000000000000100 +
b00000000000000000000000000000011 ,
1-
#1040
0-
#1050
b00000000000000000000000000000101 +
b00000000000000000000000000000100 ,
1-
#1060
0-
#1070
b00000000000000000000000000000110 +
b00000000000000000000000000000101 ,
1-
#1080
0-
#1090
b00000000000000000000000000000111 +
b00000000000000000000000000000110 ,
1-
#1100
0-
#1110
b00000000000000000000000000001000 +
b00000000000000000000000000000111 ,
1-
#1120
0-
#1130
b00000000000000000000000000001001 +
b00000000000000000000000000001000 ,
1-
#1140
0-
#1150
b00000000000000000000000000000011 *
b00000000000000000000000000000000 +
b00000000000000000000000000001001 ,
1-
#1160
0-
#1170
0&
1'
b00000000000000000000000000000011 )
b00000000000000000000000000000001 +
b00000000000000000000000000000000 ,
1-
#1180
0-
#1190
b00000000000000000000000000000010 +
b00000000000000000000000000000001 ,
1-
#1200
0-
#1210
b00000000000000000000000000000000 *
b00000000000000000000000000000000 +
b00000000000000000000000000000010 ,
1-
#1220
0-
#1230
1#
0%
0'
1(
b00000000000000000000000000000000 )
b00000000000000000000000000000001 +
b00000000000000000000000000000000 ,
1-
#1240
0-
#1250
b00000000000000000000000000000010 +
b00000000000000000000000000000001 ,
1-
#1260
0-
#1270
b00000000000000000000000000000011 +
b00000000000000000000000000000010 ,
1-
#1280
0-
#1290
b00000000000000000000000000000100 +
b00000000000000000000000000000011 ,
1-
#1300
0-
#1310
b00000000000000000000000000000101 +
b00000000000000000000000000000100 ,
1-
#1320
0-
#1330
b00000000000000000000000000000110 +
b00000000000000000000000000000101 ,
1-
#1340
0-
#1350
b00000000000000000000000000000111 +
b00000000000000000000000000000110 ,
1-
#1360
0-
#1370
b00000000000000000000000000001000 +
b00000000000000000000000000000111 ,
1-
#1380
0-
#1390
b00000000000000000000000000001001 +
b00000000000000000000000000001000 ,
1-
#1400
0-
#1410
b00000000000000000000000000000001 *
b00000000000000000000000000000000 +
b00000000000000000000000000001001 ,
1-
#1420
0-
#1430
0#
1$
b00000000000000000000000000000001 )
b00000000000000000000000000000001 +
b00000000000000000000000000000000 ,
1-
#1440
0-
#1450
b00000000000000000000000000000010 +
b00000000000000000000000000000001 ,
1-
#1460
0-
#1470
b00000000000000000000000000000010 *
b00000000000000000000000000000000 +
b00000000000000000000000000000010 ,
1-
#1480
0-
#1490
0$
1%
1&
0(
b00000000000000000000000000000010 )
b00000000000000000000000000000001 +
b00000000000000000000000000000000 ,
1-
#1500
0-
#1510
b00000000000000000000000000000010 +
b00000000000000000000000000000001 ,
1-
#1520
0-
#1530
b00000000000000000000000000000011 +
b00000000000000000000000000000010 ,
1-
#1540
0-
#1550
b00000000000000000000000000000100 +
b00000000000000000000000000000011 ,
1-
#1560
0-
#1570
b00000000000000000000000000000101 +
b00000000000000000000000000000100 ,
1-
#1580
0-
#1590
b00000000000000000000000000000110 +
b00000000000000000000000000000101 ,
1-
#1600
0-
#1610
b00000000000000000000000000000111 +
b00000000000000000000000000000110 ,
1-
#1620
0-
#1630
b00000000000000000000000000001000 +
b00000000000000000000000000000111 ,
1-
#1640
0-
#1650
b00000000000000000000000000001001 +
b00000000000000000000000000001000 ,
1-
#1660
0-
#1670
b00000000000000000000000000000011 *
b00000000000000000000000000000000 +
b00000000000000000000000000001001 ,
1-
#1680
0-
#1690
0&
1'
b00000000000000000000000000000011 )
b00000000000000000000000000000001 +
b00000000000000000000000000000000 ,
1-
#1700
0-
#1710
b00000000000000000000000000000010 +
b00000000000000000000000000000001 ,
1-
#1720
0-
#1730
b00000000000000000000000000000000 *
b00000000000000000000000000000000 +
b00000000000000000000000000000010 ,
1-
#1740
0-
#1750
1#
0%
0'
1(
b00000000000000000000000000000000 )
b00000000000000000000000000000001 +
b00000000000000000000000000000000 ,
1-
#1760
0-
#1770
b00000000000000000000000000000010 +
b00000000000000000000000000000001 ,
1-
#1780
0-
#1790
b00000000000000000000000000000011 +
b00000000000000000000000000000010 ,
1-
#1800
0-
#1810
b00000000000000000000000000000100 +
b00000000000000000000000000000011 ,
1-
#1820
0-
#1830
b00000000000000000000000000000101 +
b00000000000000000000000000000100 ,
1-
#1840
0-
#1850
b00000000000000000000000000000110 +
b00000000000000000000000000000101 ,
1-
#1860
0-
#1870
b00000000000000000000000000000111 +
b00000000000000000000000000000110 ,
1-
#1880
0-
#1890
b00000000000000000000000000001000 +
b00000000000000000000000000000111 ,
1-
#1900
0-
#1910
b00000000000000000000000000001001 +
b00000000000000000000000000001000 ,
1-
#1920
0-
#1930
b00000000000000000000000000000001 *
b00000000000000000000000000000000 +
b00000000000000000000000000001001 ,
1-
#1940
0-
#1950
0#
1$
b00000000000000000000000000000001 )
b00000000000000000000000000000001 +
b00000000000000000000000000000000 ,
1-
#1960
0-
#1970
b00000000000000000000000000000010 +
b00000000000000000000000000000001 ,
1-
#1980
0-
#1990
b00000000000000000000000000000010 *
b00000000000000000000000000000000 +
b00000000000000000000000000000010 ,
1-
#2000
0-
#2010
0$
1%
1&
0(
b00000000000000000000000000000010 )
b00000000000000000000000000000001 +
b00000000000000000000000000000000 ,
1-
#2020
0-
#2030
b00000000000000000000000000000010 +
b00000000000000000000000000000001 ,
1-
#2040
0-
#2050
b00000000000000000000000000000011 +
b00000000000000000000000000000010 ,
1-
#2060
0-
#2070
b00000000000000000000000000000100 +
b00000000000000000000000000000011 ,
1-
#2080
0-
#2090
b00000000000000000000000000000101 +
b00000000000000000000000000000100 ,
1-
#2100
0-
#2110
b00000000000000000000000000000110 +
b00000000000000000000000000000101 ,
1-
#2120
0-
#2130
b00000000000000000000000000000111 +
b00000000000000000000000000000110 ,
1-
#2140
0-
#2150
b00000000000000000000000000001000 +
b00000000000000000000000000000111 ,
1-
#2160
0-
#2170
b00000000000000000000000000001001 +
b00000000000000000000000000001000 ,
1-
#2180
0-
#2190
b00000000000000000000000000000011 *
b00000000000000000000000000000000 +
b00000000000000000000000000001001 ,
1-
#2200
0-
#2210
0&
1'
b00000000000000000000000000000011 )
b00000000000000000000000000000001 +
b00000000000000000000000000000000 ,
1-
#2220
0-
#2230
b00000000000000000000000000000010 +
b00000000000000000000000000000001 ,
1-
#2240
0-
#2250
b00000000000000000000000000000000 *
b00000000000000000000000000000000 +
b00000000000000000000000000000010 ,
1-
#2260
0-
#2270
1#
0%
0'
1(
b00000000000000000000000000000000 )
b00000000000000000000000000000001 +
b00000000000000000000000000000000 ,
1-
#2280
0-
#2290
b00000000000000000000000000000010 +
b00000000000000000000000000000001 ,
1-
#2300
0-
#2310
b00000000000000000000000000000011 +
b00000000000000000000000000000010 ,
1-
#2320
0-
#2330
b00000000000000000000000000000100 +
b00000000000000000000000000000011 ,
1-
#2340
0-
#2350
b00000000000000000000000000000101 +
b00000000000000000000000000000100 ,
1-
#2360
0-
#2370
b00000000000000000000000000000110 +
b00000000000000000000000000000101 ,
1-
#2380
0-
#2390
b00000000000000000000000000000111 +
b00000000000000000000000000000110 ,
1-
#2400
0-
#2410
b00000000000000000000000000001000 +
b00000000000000000000000000000111 ,
1-
#2420
0-
#2430
b00000000000000000000000000001001 +
b00000000000000000000000000001000 ,
1-
#2440
0-
#2450
b00000000000000000000000000000001 *
b00000000000000000000000000000000 +
b00000000000000000000000000001001 ,
1-
#2460
0-
#2470
0#
1$
b00000000000000000000000000000001 )
b00000000000000000000000000000001 +
b00000000000000000000000000000000 ,
1-
#2480
0-
#2490
b00000000000000000000000000000010 +
b00000000000000000000000000000001 ,
1-
#2500
0-
#2510
b00000000000000000000000000000010 *
b00000000000000000000000000000000 +
b00000000000000000000000000000010 ,
1-
#2520
0-
#2530
0$
1%
1&
0(
b00000000000000000000000000000010 )
b00000000000000000000000000000001 +
b00000000000000000000000000000000 ,
1-
#2540
0-
#2550
b00000000000000000000000000000010 +
b00000000000000000000000000000001 ,
1-
#2560
0-
#2570
b00000000000000000000000000000011 +
b00000000000000000000000000000010 ,
1-
#2580
0-
#2590
b00000000000000000000000000000100 +
b00000000000000000000000000000011 ,
1-
#2600
0-
#2610
b00000000000000000000000000000101 +
b00000000000000000000000000000100 ,
1-
#2620
0-
#2630
b00000000000000000000000000000110 +
b00000000000000000000000000000101 ,
1-
#2640
0-
#2650
b00000000000000000000000000000111 +
b00000000000000000000000000000110 ,
1-
#2660
0-
#2670
b00000000000000000000000000001000 +
b00000000000000000000000000000111 ,
1-
#2680
0-
#2690
b00000000000000000000000000001001 +
b00000000000000000000000000001000 ,
1-
#2700
0-
#2710
b00000000000000000000000000000011 *
b00000000000000000000000000000000 +
b00000000000000000000000000001001 ,
1-
#2720
0-
#2730
0&
1'
b00000000000000000000000000000011 )
b00000000000000000000000000000001 +
b00000000000000000000000000000000 ,
1-
#2740
0-
#2750
b00000000000000000000000000000010 +
b00000000000000000000000000000001 ,
1-
#2760
0-
#2770
b00000000000000000000000000000000 *
b00000000000000000000000000000000 +
b00000000000000000000000000000010 ,
1-
#2780
0-
#2790
1#
0%
0'
1(
b00000000000000000000000000000000 )
b00000000000000000000000000000001 +
b00000000000000000000000000000000 ,
1-
#2800
0-
#2810
b00000000000000000000000000000010 +
b00000000000000000000000000000001 ,
1-
#2820
0-
#2830
b00000000000000000000000000000011 +
b00000000000000000000000000000010 ,
1-
#2840
0-
#2850
b00000000000000000000000000000100 +
b00000000000000000000000000000011 ,
1-
#2860
0-
#2870
b00000000000000000000000000000101 +
b00000000000000000000000000000100 ,
1-
#2880
0-
#2890
b00000000000000000000000000000110 +
b00000000000000000000000000000101 ,
1-
#2900
0-
#2910
b00000000000000000000000000000111 +
b00000000000000000000000000000110 ,
1-
#2920
0-
#2930
b00000000000000000000000000001000 +
b00000000000000000000000000000111 ,
1-
#2940
0-
#2950
b00000000000000000000000000001001 +
b00000000000000000000000000001000 ,
1-
#2960
0-
#2970
b00000000000000000000000000000001 *
b00000000000000000000000000000000 +
b00000000000000000000000000001001 ,
1-
#2980
0-
#2990
0#
1$
b00000000000000000000000000000001 )
b00000000000000000000000000000001 +
b00000000000000000000000000000000 ,
1-
#3000
0-
#3010
b00000000000000000000000000000010 +
b00000000000000000000000000000001 ,
1-
#3020
0-
#3030
b00000000000000000000000000000010 *
b00000000000000000000000000000000 +
b00000000000000000000000000000010 ,
1-
#3040
0-
#3050
0$
1%
1&
0(
b00000000000000000000000000000010 )
b00000000000000000000000000000001 +
b00000000000000000000000000000000 ,
1-
#3060
0-
#3070
b00000000000000000000000000000010 +
b00000000000000000000000000000001 ,
1-
#3080
0-
#3090
b00000000000000000000000000000011 +
b00000000000000000000000000000010 ,
1-
#3100
0-
#3110
b00000000000000000000000000000100 +
b00000000000000000000000000000011 ,
1-
#3120
0-
#3130
b00000000000000000000000000000101 +
b00000000000000000000000000000100 ,
1-
#3140
0-
#3150
b00000000000000000000000000000110 +
b00000000000000000000000000000101 ,
1-
#3160
0-
#3170
b00000000000000000000000000000111 +
b00000000000000000000000000000110 ,
1-
#3180
0-
#3190
b00000000000000000000000000001000 +
b00000000000000000000000000000111 ,
1-
#3200
0-
#3210
b00000000000000000000000000001001 +
b00000000000000000000000000001000 ,
1-
#3220
0-
#3230
b00000000000000000000000000000011 *
b00000000000000000000000000000000 +
b00000000000000000000000000001001 ,
1-
#3240
0-
#3250
0&
1'
b00000000000000000000000000000011 )
b00000000000000000000000000000001 +
b00000000000000000000000000000000 ,
1-
#3260
0-
#3270
b00000000000000000000000000000010 +
b00000000000000000000000000000001 ,
1-
#3280
0-
#3290
b00000000000000000000000000000000 *
b00000000000000000000000000000000 +
b00000000000000000000000000000010 ,
1-
#3300
0-
#3310
1#
0%
0'
1(
b00000000000000000000000000000000 )
b00000000000000000000000000000001 +
b00000000000000000000000000000000 ,
1-
#3320
0-
#3330
b00000000000000000000000000000010 +
b00000000000000000000000000000001 ,
1-
#3340
0-
#3350
b00000000000000000000000000000011 +
b00000000000000000000000000000010 ,
1-
#3360
0-
#3370
b00000000000000000000000000000100 +
b00000000000000000000000000000011 ,
1-
#3380
0-
#3390
b00000000000000000000000000000101 +
b00000000000000000000000000000100 ,
1-
#3400
0-
#3410
b00000000000000000000000000000110 +
b00000000000000000000000000000101 ,
1-
#3420
0-
#3430
b00000000000000000000000000000111 +
b00000000000000000000000000000110 ,
1-
#3440
0-
#3450
b00000000000000000000000000001000 +
b00000000000000000000000000000111 ,
1-
#3460
0-
#3470
b00000000000000000000000000001001 +
b00000000000000000000000000001000 ,
1-
#3480
0-
#3490
b00000000000000000000000000000001 *
b00000000000000000000000000000000 +
b00000000000000000000000000001001 ,
1-
#3500
0-
#3510
0#
1$
b00000000000000000000000000000001 )
b00000000000000000000000000000001 +
b00000000000000000000000000000000 ,
1-
#3520
0-
#3530
b00000000000000000000000000000010 +
b00000000000000000000000000000001 ,
1-
#3540
0-
#3550
b00000000000000000000000000000010 *
b00000000000000000000000000000000 +
b00000000000000000000000000000010 ,
1-
#3560
0-
#3570
0$
1%
1&
0(
b00000000000000000000000000000010 )
b00000000000000000000000000000001 +
b00000000000000000000000000000000 ,
1-
#3580
0-
#3590
b00000000000000000000000000000010 +
b00000000000000000000000000000001 ,
1-
#3600
0-
#3610
b00000000000000000000000000000011 +
b00000000000000000000000000000010 ,
1-
#3620
0-
#3630
b00000000000000000000000000000100 +
b00000000000000000000000000000011 ,
1-
#3640
0-
#3650
b00000000000000000000000000000101 +
b00000000000000000000000000000100 ,
1-
#3660
0-
#3670
b00000000000000000000000000000110 +
b00000000000000000000000000000101 ,
1-
#3680
0-
#3690
b00000000000000000000000000000111 +
b00000000000000000000000000000110 ,
1-
#3700
0-
#3710
b00000000000000000000000000001000 +
b00000000000000000000000000000111 ,
1-
#3720
0-
#3730
b00000000000000000000000000001001 +
b00000000000000000000000000001000 ,
1-
#3740
0-
#3750
b00000000000000000000000000000011 *
b00000000000000000000000000000000 +
b00000000000000000000000000001001 ,
1-
#3760
0-
#3770
0&
1'
b00000000000000000000000000000011 )
b00000000000000000000000000000001 +
b00000000000000000000000000000000 ,
1-
#3780
0-
#3790
b00000000000000000000000000000010 +
b00000000000000000000000000000001 ,
1-
#3800
0-
#3810
b00000000000000000000000000000000 *
b00000000000000000000000000000000 +
b00000000000000000000000000000010 ,
1-
#3820
0-
#3830
1#
0%
0'
1(
b00000000000000000000000000000000 )
b00000000000000000000000000000001 +
b00000000000000000000000000000000 ,
1-
#3840
0-
#3850
b00000000000000000000000000000010 +
b00000000000000000000000000000001 ,
1-
#3860
0-
#3870
b00000000000000000000000000000011 +
b00000000000000000000000000000010 ,
1-
#3880
0-
#3890
b00000000000000000000000000000100 +
b00000000000000000000000000000011 ,
1-
#3900
0-
#3910
b00000000000000000000000000000101 +
b00000000000000000000000000000100 ,
1-
#3920
0-
#3930
b00000000000000000000000000000110 +
b00000000000000000000000000000101 ,
1-
#3940
0-
#3950
b00000000000000000000000000000111 +
b00000000000000000000000000000110 ,
1-
#3960
0-
#3970
b00000000000000000000000000001000 +
b00000000000000000000000000000111 ,
1-
#3980
0-
#3990
b00000000000000000000000000001001 +
b00000000000000000000000000001000 ,
1-
#4000
0-
#4010
b00000000000000000000000000000001 *
b00000000000000000000000000000000 +
b00000000000000000000000000001001 ,
1-
#4020
0-
#4030
0#
1$
b00000000000000000000000000000001 )
b00000000000000000000000000000001 +
b00000000000000000000000000000000 ,
1-
#4040
0-
#4050
b00000000000000000000000000000010 +
b00000000000000000000000000000001 ,
1-
#4060
0-
#4070
b00000000000000000000000000000010 *
b00000000000000000000000000000000 +
b00000000000000000000000000000010 ,
1-
#4080
0-
#4090
0$
1%
1&
0(
b00000000000000000000000000000010 )
b00000000000000000000000000000001 +
b00000000000000000000000000000000 ,
1-
#4100
0-
#4110
b00000000000000000000000000000010 +
b00000000000000000000000000000001 ,
1-
#4120
0-
#4130
b00000000000000000000000000000011 +
b00000000000000000000000000000010 ,
1-
#4140
0-
#4150
b00000000000000000000000000000100 +
b00000000000000000000000000000011 ,
1-
#4160
0-
#4170
b00000000000000000000000000000101 +
b00000000000000000000000000000100 ,
1-
#4180
0-
#4190
b00000000000000000000000000000110 +
b00000000000000000000000000000101 ,
1-
#4200
0-
#4210
b00000000000000000000000000000111 +
b00000000000000000000000000000110 ,
1-
#4220
0-
#4230
b00000000000000000000000000001000 +
b00000000000000000000000000000111 ,
1-
#4240
0-
#4250
b00000000000000000000000000001001 +
b00000000000000000000000000001000 ,
1-
#4260
0-
#4270
b00000000000000000000000000000011 *
b00000000000000000000000000000000 +
b00000000000000000000000000001001 ,
1-
#4280
0-
#4290
0&
1'
b00000000000000000000000000000011 )
b00000000000000000000000000000001 +
b00000000000000000000000000000000 ,
1-
#4300
0-
#4310
b00000000000000000000000000000010 +
b00000000000000000000000000000001 ,
1-
#4320
0-
#4330
b00000000000000000000000000000000 *
b00000000000000000000000000000000 +
b00000000000000000000000000000010 ,
1-
#4340
0-
#4350
1#
0%
0'
1(
b00000000000000000000000000000000 )
b00000000000000000000000000000001 +
b00000000000000000000000000000000 ,
1-
#4360
0-
#4370
b00000000000000000000000000000010 +
b00000000000000000000000000000001 ,
1-
#4380
0-
#4390
b00000000000000000000000000000011 +
b00000000000000000000000000000010 ,
1-
#4400
0-
#4410
b00000000000000000000000000000100 +
b00000000000000000000000000000011 ,
1-
#4420
0-
#4430
b00000000000000000000000000000101 +
b00000000000000000000000000000100 ,
1-
#4440
0-
#4450
b00000000000000000000000000000110 +
b00000000000000000000000000000101 ,
1-
#4460
0-
#4470
b00000000000000000000000000000111 +
b00000000000000000000000000000110 ,
1-
#4480
0-
#4490
b00000000000000000000000000001000 +
b00000000000000000000000000000111 ,
1-
#4500
0-
#4510
b00000000000000000000000000001001 +
b00000000000000000000000000001000 ,
1-
#4520
0-
#4530
b00000000000000000000000000000001 *
b00000000000000000000000000000000 +
b00000000000000000000000000001001 ,
1-
#4540
0-
#4550
0#
1$
b00000000000000000000000000000001 )
b00000000000000000000000000000001 +
b00000000000000000000000000000000 ,
1-
#4560
0-
#4570
b00000000000000000000000000000010 +
b00000000000000000000000000000001 ,
1-
#4580
0-
#4590
b00000000000000000000000000000010 *
b00000000000000000000000000000000 +
b00000000000000000000000000000010 ,
1-
#4600
0-
#4610
0$
1%
1&
0(
b00000000000000000000000000000010 )
b00000000000000000000000000000001 +
b00000000000000000000000000000000 ,
1-
#4620
0-
#4630
b00000000000000000000000000000010 +
b00000000000000000000000000000001 ,
1-
#4640
0-
#4650
b00000000000000000000000000000011 +
b00000000000000000000000000000010 ,
1-
#4660
0-
#4670
b00000000000000000000000000000100 +
b00000000000000000000000000000011 ,
1-
#4680
0-
#4690
b00000000000000000000000000000101 +
b00000000000000000000000000000100 ,
1-
#4700
0-
#4710
b00000000000000000000000000000110 +
b00000000000000000000000000000101 ,
1-
#4720
0-
#4730
b00000000000000000000000000000111 +
b00000000000000000000000000000110 ,
1-
#4740
0-
#4750
b00000000000000000000000000001000 +
b00000000000000000000000000000111 ,
1-
#4760
0-
#4770
b00000000000000000000000000001001 +
b00000000000000000000000000001000 ,
1-
#4780
0-
#4790
b00000000000000000000000000000011 *
b00000000000000000000000000000000 +
b00000000000000000000000000001001 ,
1-
#4800
0-
#4810
0&
1'
b00000000000000000000000000000011 )
b00000000000000000000000000000001 +
b00000000000000000000000000000000 ,
1-
#4820
0-
#4830
b00000000000000000000000000000010 +
b00000000000000000000000000000001 ,
1-
#4840
0-
#4850
b00000000000000000000000000000000 *
b00000000000000000000000000000000 +
b00000000000000000000000000000010 ,
1-
#4860
0-
#4870
1#
0%
0'
1(
b00000000000000000000000000000000 )
b00000000000000000000000000000001 +
b00000000000000000000000000000000 ,
1-
#4880
0-
#4890
b00000000000000000000000000000010 +
b00000000000000000000000000000001 ,
1-
#4900
0-
#4910
b00000000000000000000000000000011 +
b00000000000000000000000000000010 ,
1-
#4920
0-
#4930
b00000000000000000000000000000100 +
b00000000000000000000000000000011 ,
1-
#4940
0-
#4950
b00000000000000000000000000000101 +
b00000000000000000000000000000100 ,
1-
#4960
0-
#4970
b00000000000000000000000000000110 +
b00000000000000000000000000000101 ,
1-
#4980
0-
#4990
b00000000000000000000000000000111 +
b00000000000000000000000000000110 ,
1-
#5000
0-
#5010
b00000000000000000000000000001000 +
b00000000000000000000000000000111 ,
1-
#5020
0-
#5030
b00000000000000000000000000001001 +
b00000000000000000000000000001000 ,
1-
#5040
0-
#5050
b00000000000000000000000000000001 *
b00000000000000000000000000000000 +
b00000000000000000000000000001001 ,
1-
#5060
0-
#5070
0#
1$
b00000000000000000000000000000001 )
b00000000000000000000000000000001 +
b00000000000000000000000000000000 ,
1-
#5080
0-
#5090
b00000000000000000000000000000010 +
b00000000000000000000000000000001 ,
1-
#5100
0-
#5110
b00000000000000000000000000000010 *
b00000000000000000000000000000000 +
b00000000000000000000000000000010 ,
1-
#5120
0-
